langchain_xai/__init__.py
langchain_xai/chat_models.py
langchain_xai/py.typed
langchain_xai/data/__init__.py
langchain_xai/data/_profiles.py
langchain_xai-1.2.1.dist-info/METADATA
langchain_xai-1.2.1.dist-info/WHEEL
langchain_xai-1.2.1.dist-info/licenses/LICENSE
langchain_xai-1.2.1.dist-info/RECORD
