Metadata-Version: 2.4
Name: langchain-xai
Version: 1.2.1
Summary: An integration package connecting xAI and LangChain
Project-URL: Homepage, https://docs.langchain.com/oss/python/integrations/providers/xai
Project-URL: Documentation, https://reference.langchain.com/python/integrations/langchain_xai/
Project-URL: Source, https://github.com/langchain-ai/langchain/tree/master/libs/partners/xai
Project-URL: Changelog, https://github.com/langchain-ai/langchain/releases?q=%22langchain-xai%22
Project-URL: Twitter, https://x.com/LangChainAI
Project-URL: Slack, https://www.langchain.com/join-community
Project-URL: Reddit, https://www.reddit.com/r/LangChain/
License: MIT
License-File: LICENSE
Requires-Python: <4.0.0,>=3.10.0
Requires-Dist: aiohttp<4.0.0,>=3.9.1
Requires-Dist: langchain-core<2.0.0,>=1.2.6
Requires-Dist: langchain-openai<2.0.0,>=1.1.6
Requires-Dist: requests<3.0.0,>=2.0.0
